model_parser/__init__.py
model_parser/__main__.py
model_parser/custom_types.py
model_parser/mapper.py
model_parser/pydantic_parser.py
pydantic_model_parser-1.0.1.dist-info/METADATA
pydantic_model_parser-1.0.1.dist-info/WHEEL
pydantic_model_parser-1.0.1.dist-info/top_level.txt
pydantic_model_parser-1.0.1.dist-info/RECORD
