Metadata-Version: 2.1
Name: pydantic-model-parser
Version: 1.0.1
Summary: A simple package to transform/map dictionaries, before parsing it into Pydantic.
Home-page: https://github.com/ctgjdw/pydantic-model-parser
Author: CTGJDW
Author-email: gohchunteck@hotmail.com
License: UNKNOWN
Platform: UNKNOWN
Classifier: Programming Language :: Python :: 3
Classifier: Programming Language :: Python :: 3.8
Requires-Dist: pydantic (>=1.9.0)
Requires-Dist: pydash (>=5.0.0)
